<?xml version="1.0" encoding="utf-8" standalone="no"?>
<billStatus>
  <version>3.0.0</version>
  <bill>
    <number>163</number>
    <updateDate>2025-09-05T08:05:59Z</updateDate>
    <updateDateIncludingText>2025-09-05T08:05:59Z</updateDateIncludingText>
    <originChamber>House</originChamber>
    <originChamberCode>H</originChamberCode>
    <type>HRES</type>
    <introducedDate>2025-02-25</introducedDate>
    <congress>119</congress>
    <legislationUrl>https://www.congress.gov/bill/119th-congress/house-resolution/163</legislationUrl>
    <cdata/>
    <committees>
      <item>
        <systemCode>hsed00</systemCode>
        <name>Education and Workforce Committee</name>
        <chamber>House</chamber>
        <type>Standing</type>
        <activities>
          <item>
            <name>Referred To</name>
            <date>2025-02-25T15:01:00Z</date>
          </item>
        </activities>
      </item>
    </committees>
    <actions>
      <item>
        <actionDate>2025-02-25</actionDate>
        <text>Referred to the House Committee on Education and Workforce.</text>
        <type>IntroReferral</type>
        <actionCode>H11100</actionCode>
        <sourceSystem>
          <code>2</code>
          <name>House floor actions</name>
        </sourceSystem>
        <committees>
          <item>
            <systemCode>hsed00</systemCode>
            <name>Education and Workforce Committee</name>
          </item>
        </committees>
      </item>
      <item>
        <actionDate>2025-02-25</actionDate>
        <text>Submitted in House</text>
        <type>Committee</type>
        <actionCode>H12100</actionCode>
        <sourceSystem>
          <code>9</code>
          <name>Library of Congress</name>
        </sourceSystem>
      </item>
    </actions>
    <sponsors>
      <item>
        <bioguideId>H001058</bioguideId>
        <fullName>Rep. Huizenga, Bill [R-MI-4]</fullName>
        <firstName>Bill</firstName>
        <lastName>Huizenga</lastName>
        <party>R</party>
        <state>MI</state>
        <district>4</district>
        <isByRequest>N</isByRequest>
      </item>
    </sponsors>
    <cosponsors>
      <item>
        <bioguideId>M001194</bioguideId>
        <fullName>Rep. Moolenaar, John R. [R-MI-2]</fullName>
        <firstName>John</firstName>
        <lastName>Moolenaar</lastName>
        <party>R</party>
        <state>MI</state>
        <middleName>R.</middleName>
        <district>2</district>
        <sponsorshipDate>2025-02-25</sponsorshipDate>
        <isOriginalCosponsor>True</isOriginalCosponsor>
      </item>
      <item>
        <bioguideId>T000488</bioguideId>
        <fullName>Rep. Thanedar, Shri [D-MI-13]</fullName>
        <firstName>Shri</firstName>
        <lastName>Thanedar</lastName>
        <party>D</party>
        <state>MI</state>
        <district>13</district>
        <sponsorshipDate>2025-02-25</sponsorshipDate>
        <isOriginalCosponsor>True</isOriginalCosponsor>
      </item>
      <item>
        <bioguideId>D000624</bioguideId>
        <fullName>Rep. Dingell, Debbie [D-MI-6]</fullName>
        <firstName>Debbie</firstName>
        <lastName>Dingell</lastName>
        <party>D</party>
        <state>MI</state>
        <district>6</district>
        <sponsorshipDate>2025-02-25</sponsorshipDate>
        <isOriginalCosponsor>True</isOriginalCosponsor>
      </item>
      <item>
        <bioguideId>M001237</bioguideId>
        <fullName>Rep. McDonald Rivet, Kristen [D-MI-8]</fullName>
        <firstName>Kristen</firstName>
        <lastName>McDonald Rivet</lastName>
        <party>D</party>
        <state>MI</state>
        <district>8</district>
        <sponsorshipDate>2025-02-25</sponsorshipDate>
        <isOriginalCosponsor>True</isOriginalCosponsor>
      </item>
      <item>
        <bioguideId>S001221</bioguideId>
        <fullName>Rep. Scholten, Hillary J. [D-MI-3]</fullName>
        <firstName>Hillary</firstName>
        <lastName>Scholten</lastName>
        <party>D</party>
        <state>MI</state>
        <middleName>J.</middleName>
        <district>3</district>
        <sponsorshipDate>2025-02-25</sponsorshipDate>
        <isOriginalCosponsor>True</isOriginalCosponsor>
      </item>
      <item>
        <bioguideId>J000307</bioguideId>
        <fullName>Rep. James, John [R-MI-10]</fullName>
        <firstName>John</firstName>
        <lastName>James</lastName>
        <party>R</party>
        <state>MI</state>
        <district>10</district>
        <sponsorshipDate>2025-02-25</sponsorshipDate>
        <isOriginalCosponsor>True</isOriginalCosponsor>
      </item>
      <item>
        <bioguideId>B001301</bioguideId>
        <fullName>Rep. Bergman, Jack [R-MI-1]</fullName>
        <firstName>Jack</firstName>
        <lastName>Bergman</lastName>
        <party>R</party>
        <state>MI</state>
        <district>1</district>
        <sponsorshipDate>2025-02-26</sponsorshipDate>
        <isOriginalCosponsor>False</isOriginalCosponsor>
      </item>
      <item>
        <bioguideId>B001321</bioguideId>
        <fullName>Rep. Barrett, Tom [R-MI-7]</fullName>
        <firstName>Tom</firstName>
        <lastName>Barrett</lastName>
        <party>R</party>
        <state>MI</state>
        <district>7</district>
        <sponsorshipDate>2025-03-24</sponsorshipDate>
        <isOriginalCosponsor>False</isOriginalCosponsor>
      </item>
      <item>
        <bioguideId>K000401</bioguideId>
        <fullName>Rep. Kiley, Kevin [R-CA-3]</fullName>
        <firstName>Kevin</firstName>
        <lastName>Kiley</lastName>
        <party>R</party>
        <state>CA</state>
        <district>3</district>
        <sponsorshipDate>2025-09-04</sponsorshipDate>
        <isOriginalCosponsor>False</isOriginalCosponsor>
      </item>
    </cosponsors>
    <policyArea>
      <name>Education</name>
    </policyArea>
    <subjects>
      <legislativeSubjects/>
      <policyArea>
        <name>Education</name>
        <updateDate>2025-03-01T16:37:23Z</updateDate>
      </policyArea>
    </subjects>
    <summaries>
      <summary>
        <versionCode>00</versionCode>
        <actionDate>2025-02-25</actionDate>
        <actionDesc>Introduced in House</actionDesc>
        <updateDate>2025-08-12T21:18:04Z</updateDate>
        <cdata>
          <text>&lt;p&gt;This resolution recognizes the goal of education in U.S. schools as that of ensuring that&amp;nbsp;virtually every student achieves grade-level reading proficiency. It also encourages state and local governments, including educational agencies, to collaborate with private organizations that offer proven literacy programs to (1) identify and implement effective solutions to address illiteracy, and (2) create adult literacy initiatives for adults with reading skills below an 8th grade level.&lt;/p&gt;</text>
        </cdata>
      </summary>
    </summaries>
    <title>Expressing the sense of the House of Representatives that the goal of education in schools across America shall be that virtually every student in the United States achieves grade-level reading proficiency, providing them with the foundation to develop the skills and knowledge needed for success in school, work, and life.</title>
    <titles>
      <item>
        <titleType>Official Title as Introduced</titleType>
        <titleTypeCode>6</titleTypeCode>
        <title>Expressing the sense of the House of Representatives that the goal of education in schools across America shall be that virtually every student in the United States achieves grade-level reading proficiency, providing them with the foundation to develop the skills and knowledge needed for success in school, work, and life.</title>
        <updateDate>2025-02-26T11:18:23Z</updateDate>
        <billTextVersionName>Introduced in House</billTextVersionName>
        <billTextVersionCode>IH</billTextVersionCode>
      </item>
      <item>
        <titleType>Display Title</titleType>
        <titleTypeCode>45</titleTypeCode>
        <title>Expressing the sense of the House of Representatives that the goal of education in schools across America shall be that virtually every student in the United States achieves grade-level reading proficiency, providing them with the foundation to develop the skills and knowledge needed for success in school, work, and life.</title>
        <updateDate>2025-02-26T09:06:03Z</updateDate>
      </item>
    </titles>
    <textVersions>
      <item>
        <type>Introduced in House</type>
        <date>2025-02-25T05:00:00Z</date>
        <formats>
          <item>
            <url>https://www.govinfo.gov/content/pkg/BILLS-119hres163ih/xml/BILLS-119hres163ih.xml</url>
          </item>
        </formats>
      </item>
    </textVersions>
    <latestAction>
      <actionDate>2025-02-25</actionDate>
      <text>Referred to the House Committee on Education and Workforce.</text>
    </latestAction>
  </bill>
  <dublinCore xmlns:dc="http://purl.org/dc/elements/1.1/">
    <dc:format>text/xml</dc:format>
    <dc:language>EN</dc:language>
    <dc:rights>Pursuant to Title 17 Section 105 of the United States Code, this file is not subject to copyright protection and is in the public domain.</dc:rights>
    <dc:contributor>Congressional Research Service, Library of Congress</dc:contributor>
    <dc:description>This file contains bill summaries and statuses for federal legislation. A bill summary describes the most significant provisions of a piece of legislation and details the effects the legislative text may have on current law and federal programs. Bill summaries are authored by the Congressional Research Service (CRS) of the Library of Congress. As stated in Public Law 91-510 (2 USC 166 (d)(6)), one of the duties of CRS is "to prepare summaries and digests of bills and resolutions of a public general nature introduced in the Senate or House of Representatives". For more information, refer to the User Guide that accompanies this file.</dc:description>
  </dublinCore>
</billStatus>
