<?xml version="1.0" encoding="utf-8" standalone="no"?>
<billStatus>
  <version>3.0.0</version>
  <bill>
    <number>281</number>
    <updateDate>2025-12-05T22:55:17Z</updateDate>
    <updateDateIncludingText>2025-12-05T22:55:17Z</updateDateIncludingText>
    <originChamber>House</originChamber>
    <originChamberCode>H</originChamberCode>
    <type>HRES</type>
    <introducedDate>2025-03-31</introducedDate>
    <congress>119</congress>
    <legislationUrl>https://www.congress.gov/bill/119th-congress/house-resolution/281</legislationUrl>
    <cdata/>
    <committees>
      <item>
        <systemCode>hsfa00</systemCode>
        <name>Foreign Affairs Committee</name>
        <chamber>House</chamber>
        <type>Standing</type>
        <activities>
          <item>
            <name>Referred To</name>
            <date>2025-03-31T16:05:15Z</date>
          </item>
        </activities>
      </item>
    </committees>
    <relatedBills>
      <item>
        <title>Urging the people of the United States to observe the month of March 2025 as "Bulgarian-American Heritage Month".</title>
        <congress>119</congress>
        <number>291</number>
        <type>HRES</type>
        <latestAction>
          <actionDate>2025-04-02</actionDate>
          <text>Referred to the House Committee on Foreign Affairs.</text>
        </latestAction>
        <relationshipDetails>
          <item>
            <type>Identical bill</type>
            <identifiedBy>CRS</identifiedBy>
          </item>
        </relationshipDetails>
      </item>
    </relatedBills>
    <actions>
      <item>
        <actionDate>2025-03-31</actionDate>
        <text>Referred to the House Committee on Foreign Affairs.</text>
        <type>IntroReferral</type>
        <actionCode>H11100</actionCode>
        <sourceSystem>
          <code>2</code>
          <name>House floor actions</name>
        </sourceSystem>
        <committees>
          <item>
            <systemCode>hsfa00</systemCode>
            <name>Foreign Affairs Committee</name>
          </item>
        </committees>
      </item>
      <item>
        <actionDate>2025-03-31</actionDate>
        <text>Submitted in House</text>
        <type>IntroReferral</type>
        <actionCode>H11100</actionCode>
        <sourceSystem>
          <code>9</code>
          <name>Library of Congress</name>
        </sourceSystem>
      </item>
      <item>
        <actionDate>2025-03-31</actionDate>
        <text>Submitted in House</text>
        <type>IntroReferral</type>
        <actionCode>1025</actionCode>
        <sourceSystem>
          <code>9</code>
          <name>Library of Congress</name>
        </sourceSystem>
      </item>
    </actions>
    <sponsors>
      <item>
        <bioguideId>W000795</bioguideId>
        <fullName>Rep. Wilson, Joe [R-SC-2]</fullName>
        <firstName>Joe</firstName>
        <lastName>Wilson</lastName>
        <party>R</party>
        <state>SC</state>
        <district>2</district>
        <isByRequest>N</isByRequest>
      </item>
    </sponsors>
    <cosponsors>
      <item>
        <bioguideId>S001190</bioguideId>
        <fullName>Rep. Schneider, Bradley Scott [D-IL-10]</fullName>
        <firstName>Bradley</firstName>
        <lastName>Schneider</lastName>
        <party>D</party>
        <state>IL</state>
        <middleName>Scott</middleName>
        <district>10</district>
        <sponsorshipDate>2025-03-31</sponsorshipDate>
        <isOriginalCosponsor>True</isOriginalCosponsor>
      </item>
      <item>
        <bioguideId>D000628</bioguideId>
        <fullName>Rep. Dunn, Neal P. [R-FL-2]</fullName>
        <firstName>Neal</firstName>
        <lastName>Dunn</lastName>
        <party>R</party>
        <state>FL</state>
        <middleName>P.</middleName>
        <district>2</district>
        <sponsorshipDate>2025-03-31</sponsorshipDate>
        <isOriginalCosponsor>True</isOriginalCosponsor>
      </item>
      <item>
        <bioguideId>N000015</bioguideId>
        <fullName>Rep. Neal, Richard E. [D-MA-1]</fullName>
        <firstName>Richard</firstName>
        <lastName>Neal</lastName>
        <party>D</party>
        <state>MA</state>
        <middleName>E.</middleName>
        <district>1</district>
        <sponsorshipDate>2025-03-31</sponsorshipDate>
        <isOriginalCosponsor>True</isOriginalCosponsor>
      </item>
    </cosponsors>
    <policyArea>
      <name>International Affairs</name>
    </policyArea>
    <subjects>
      <legislativeSubjects/>
      <policyArea>
        <name>International Affairs</name>
        <updateDate>2025-05-23T13:32:59Z</updateDate>
      </policyArea>
    </subjects>
    <title>Urging the people of the United States to observe the month of March 2025 as "Bulgarian-American Heritage Month".</title>
    <titles>
      <item>
        <titleType>Official Title as Introduced</titleType>
        <titleTypeCode>6</titleTypeCode>
        <title>Urging the people of the United States to observe the month of March 2025 as "Bulgarian-American Heritage Month".</title>
        <updateDate>2025-04-01T13:18:28Z</updateDate>
        <billTextVersionName>Introduced in House</billTextVersionName>
        <billTextVersionCode>IH</billTextVersionCode>
      </item>
      <item>
        <titleType>Display Title</titleType>
        <titleTypeCode>45</titleTypeCode>
        <title>Urging the people of the United States to observe the month of March 2025 as "Bulgarian-American Heritage Month".</title>
        <updateDate>2025-04-01T08:06:00Z</updateDate>
      </item>
    </titles>
    <textVersions>
      <item>
        <type>Introduced in House</type>
        <date>2025-03-31T04:00:00Z</date>
        <formats>
          <item>
            <url>https://www.govinfo.gov/content/pkg/BILLS-119hres281ih/xml/BILLS-119hres281ih.xml</url>
          </item>
        </formats>
      </item>
    </textVersions>
    <latestAction>
      <actionDate>2025-03-31</actionDate>
      <text>Referred to the House Committee on Foreign Affairs.</text>
    </latestAction>
  </bill>
  <dublinCore xmlns:dc="http://purl.org/dc/elements/1.1/">
    <dc:format>text/xml</dc:format>
    <dc:language>EN</dc:language>
    <dc:rights>Pursuant to Title 17 Section 105 of the United States Code, this file is not subject to copyright protection and is in the public domain.</dc:rights>
    <dc:contributor>Congressional Research Service, Library of Congress</dc:contributor>
    <dc:description>This file contains bill summaries and statuses for federal legislation. A bill summary describes the most significant provisions of a piece of legislation and details the effects the legislative text may have on current law and federal programs. Bill summaries are authored by the Congressional Research Service (CRS) of the Library of Congress. As stated in Public Law 91-510 (2 USC 166 (d)(6)), one of the duties of CRS is "to prepare summaries and digests of bills and resolutions of a public general nature introduced in the Senate or House of Representatives". For more information, refer to the User Guide that accompanies this file.</dc:description>
  </dublinCore>
</billStatus>
