<?xml version="1.0" encoding="utf-8" standalone="no"?>
<billStatus>
  <version>3.0.0</version>
  <bill>
    <number>294</number>
    <updateDate>2025-10-09T00:11:26Z</updateDate>
    <updateDateIncludingText>2025-10-09T00:11:26Z</updateDateIncludingText>
    <originChamber>House</originChamber>
    <originChamberCode>H</originChamberCode>
    <type>HRES</type>
    <introducedDate>2025-04-07</introducedDate>
    <congress>119</congress>
    <legislationUrl>https://www.congress.gov/bill/119th-congress/house-resolution/294</legislationUrl>
    <cdata/>
    <committees>
      <item>
        <systemCode>hsru00</systemCode>
        <name>Rules Committee</name>
        <chamber>House</chamber>
        <type>Standing</type>
        <activities>
          <item>
            <name>Reported Original Measure</name>
            <date>2025-04-07T23:20:39Z</date>
          </item>
        </activities>
      </item>
    </committees>
    <committeeReports>
      <committeeReport>
        <citation>H. Rept. 119-50</citation>
      </committeeReport>
    </committeeReports>
    <relatedBills>
      <item>
        <title>A joint resolution disapproving the rule submitted by the Bureau of Consumer Financial Protection relating to "Overdraft Lending: Very Large Financial Institutions".</title>
        <congress>119</congress>
        <number>18</number>
        <type>SJRES</type>
        <latestAction>
          <actionDate>2025-05-09</actionDate>
          <text>Became Public Law No: 119-10.</text>
        </latestAction>
        <relationshipDetails>
          <item>
            <type>Related bill</type>
            <identifiedBy>House</identifiedBy>
          </item>
          <item>
            <type>Procedurally related</type>
            <identifiedBy>House</identifiedBy>
          </item>
        </relationshipDetails>
      </item>
      <item>
        <title>A joint resolution disapproving the rule submitted by the Bureau of Consumer Financial Protection relating to "Defining Larger Participants of a Market for General-Use Digital Consumer Payment Applications".</title>
        <congress>119</congress>
        <number>28</number>
        <type>SJRES</type>
        <latestAction>
          <actionDate>2025-05-09</actionDate>
          <text>Became Public Law No: 119-11.</text>
        </latestAction>
        <relationshipDetails>
          <item>
            <type>Related bill</type>
            <identifiedBy>House</identifiedBy>
          </item>
          <item>
            <type>Procedurally related</type>
            <identifiedBy>House</identifiedBy>
          </item>
        </relationshipDetails>
      </item>
      <item>
        <title>NORRA of 2025</title>
        <congress>119</congress>
        <number>1526</number>
        <type>HR</type>
        <latestAction>
          <actionDate>2025-04-10</actionDate>
          <text>Received in the Senate and Read twice and referred to the Committee on the Judiciary.</text>
        </latestAction>
        <relationshipDetails>
          <item>
            <type>Related bill</type>
            <identifiedBy>House</identifiedBy>
          </item>
          <item>
            <type>Procedurally related</type>
            <identifiedBy>House</identifiedBy>
          </item>
        </relationshipDetails>
      </item>
      <item>
        <title>SAVE Act</title>
        <congress>119</congress>
        <number>22</number>
        <type>HR</type>
        <latestAction>
          <actionDate>2025-04-10</actionDate>
          <text>Received in the Senate.</text>
        </latestAction>
        <relationshipDetails>
          <item>
            <type>Procedurally related</type>
            <identifiedBy>House</identifiedBy>
          </item>
        </relationshipDetails>
      </item>
      <item>
        <title>Providing for consideration of the joint resolution (S.J. Res. 18) disapproving the rule submitted by the Bureau of Consumer Financial Protection relating to "Overdraft Lending: Very Large Financial Institutions''; providing for consideration of the joint resolution (S.J. Res. 28) disapproving the rule submitted by the Bureau of Consumer Financial Protection relating to ''Defining Larger Participants of a Market for General-Use Digital Consumer Payment Applications''; providing for consideration of the bill (H.R. 1526) to amend title 28, United States Code, to limit the authority of district courts to provide injunctive relief, and for other purposes; providing for consideration of the bill (H.R. 22) to amend the National Voter Registration Act of 1993 to require proof of United States citizenship to register an individual to vote in elections for Federal office, and for other purposes; and for other purposes.</title>
        <congress>119</congress>
        <number>282</number>
        <type>HRES</type>
        <latestAction>
          <actionDate>2025-04-01</actionDate>
          <text>Motion to reconsider laid on the table Agreed to without objection.</text>
          <actionTime>14:16:03</actionTime>
        </latestAction>
        <relationshipDetails>
          <item>
            <type>Related bill</type>
            <identifiedBy>CRS</identifiedBy>
          </item>
        </relationshipDetails>
      </item>
      <item>
        <title>Providing for the announcement of pairs from a written list furnished to the Clerk, and for other purposes.</title>
        <congress>119</congress>
        <number>293</number>
        <type>HRES</type>
        <latestAction>
          <actionDate>2025-04-08</actionDate>
          <text>Pursuant to the provisions of H. Res. 294, H. Res. 293 is considered passed House. (consideration: CR H1481: 1; text: CR H1481)</text>
          <actionTime>15:23:30</actionTime>
        </latestAction>
        <relationshipDetails>
          <item>
            <type>Procedurally related</type>
            <identifiedBy>House</identifiedBy>
          </item>
          <item>
            <type>Procedurally related</type>
            <identifiedBy>House</identifiedBy>
          </item>
        </relationshipDetails>
      </item>
      <item>
        <title>Providing for the consideration of S.J. Res. 18, S.J. Res 24, H.R. 1526, and H.R. 22.</title>
        <congress>119</congress>
        <number>287</number>
        <type>HRES</type>
        <latestAction>
          <actionDate>2025-04-01</actionDate>
          <text>Referred to the House Committee on Rules.</text>
        </latestAction>
        <relationshipDetails>
          <item>
            <type>Related bill</type>
            <identifiedBy>CRS</identifiedBy>
          </item>
        </relationshipDetails>
      </item>
    </relatedBills>
    <actions>
      <item>
        <actionDate>2025-04-08</actionDate>
        <actionTime>15:23:14</actionTime>
        <text>Motion to reconsider laid on the table Agreed to without objection.</text>
        <type>Floor</type>
        <actionCode>H38310</actionCode>
        <sourceSystem>
          <code>2</code>
          <name>House floor actions</name>
        </sourceSystem>
      </item>
      <item>
        <actionDate>2025-04-08</actionDate>
        <actionTime>15:23:12</actionTime>
        <text>On agreeing to the resolution Agreed to by recorded vote: 213 - 211 (Roll no. 92). (text: CR H1473: 2)</text>
        <type>Floor</type>
        <actionCode>H37100</actionCode>
        <sourceSystem>
          <code>2</code>
          <name>House floor actions</name>
        </sourceSystem>
        <recordedVotes>
          <recordedVote>
            <rollNumber>92</rollNumber>
            <url>https://clerk.house.gov/evs/2025/roll092.xml</url>
            <chamber>House</chamber>
            <congress>119</congress>
            <date>2025-04-08T19:23:12Z</date>
            <sessionNumber>1</sessionNumber>
          </recordedVote>
        </recordedVotes>
      </item>
      <item>
        <actionDate>2025-04-08</actionDate>
        <actionTime>15:23:12</actionTime>
        <text>Passed/agreed to in House: On agreeing to the resolution Agreed to by recorded vote: 213 - 211 (Roll no. 92). (text: CR H1473: 2)</text>
        <type>Floor</type>
        <actionCode>8000</actionCode>
        <sourceSystem>
          <code>9</code>
          <name>Library of Congress</name>
        </sourceSystem>
        <recordedVotes>
          <recordedVote>
            <rollNumber>92</rollNumber>
            <url>https://clerk.house.gov/evs/2025/roll092.xml</url>
            <chamber>House</chamber>
            <congress>119</congress>
            <date>2025-04-08T19:23:12Z</date>
            <sessionNumber>1</sessionNumber>
          </recordedVote>
        </recordedVotes>
      </item>
      <item>
        <actionDate>2025-04-08</actionDate>
        <actionTime>15:14:57</actionTime>
        <text>On ordering the previous question Agreed to by the Yeas and Nays: 213 - 211 (Roll no. 91).</text>
        <type>Floor</type>
        <actionCode>H35000</actionCode>
        <sourceSystem>
          <code>2</code>
          <name>House floor actions</name>
        </sourceSystem>
        <recordedVotes>
          <recordedVote>
            <rollNumber>91</rollNumber>
            <url>https://clerk.house.gov/evs/2025/roll091.xml</url>
            <chamber>House</chamber>
            <congress>119</congress>
            <date>2025-04-08T19:14:57Z</date>
            <sessionNumber>1</sessionNumber>
          </recordedVote>
        </recordedVotes>
      </item>
      <item>
        <actionDate>2025-04-08</actionDate>
        <actionTime>14:15:23</actionTime>
        <text>Considered as unfinished business. (consideration: CR H1480-1481)</text>
        <type>Floor</type>
        <actionCode>H30000</actionCode>
        <sourceSystem>
          <code>2</code>
          <name>House floor actions</name>
        </sourceSystem>
      </item>
      <item>
        <actionDate>2025-04-08</actionDate>
        <actionTime>13:13:30</actionTime>
        <text>POSTPONED PROCEEDINGS - At the conclusion of debate on H. Res. 294, the Chair put the question on ordering the previous question and by voice vote announced that the ayes had prevailed. Mr. McGovern demanded the yeas and nays and the Chair postponed further proceedings until a time to be announced.</text>
        <type>Floor</type>
        <actionCode>H8D000</actionCode>
        <sourceSystem>
          <code>2</code>
          <name>House floor actions</name>
        </sourceSystem>
      </item>
      <item>
        <actionDate>2025-04-08</actionDate>
        <actionTime>12:14:30</actionTime>
        <text>DEBATE - The House proceeded with one hour of debate on H. Res. 294.</text>
        <type>Floor</type>
        <actionCode>H8D000</actionCode>
        <sourceSystem>
          <code>2</code>
          <name>House floor actions</name>
        </sourceSystem>
      </item>
      <item>
        <actionDate>2025-04-08</actionDate>
        <actionTime>12:11:17</actionTime>
        <text>Considered as privileged matter. (consideration: CR H1473-1480)</text>
        <type>Floor</type>
        <actionCode>H30000</actionCode>
        <sourceSystem>
          <code>2</code>
          <name>House floor actions</name>
        </sourceSystem>
      </item>
      <item>
        <actionDate>2025-04-07</actionDate>
        <text>Placed on the House Calendar, Calendar No. 15.</text>
        <type>Calendars</type>
        <actionCode>H12420</actionCode>
        <sourceSystem>
          <code>2</code>
          <name>House floor actions</name>
        </sourceSystem>
      </item>
      <item>
        <actionDate>2025-04-07</actionDate>
        <actionTime>19:20:40</actionTime>
        <text>The resolution provides for consideration of H.R. 22, H.R. 1526, S.J. Res. 18, and S.J. Res. 28 under a closed rule. The resolution provides for one hour of debate on each measure and one motion to recommit on H.R. 22 and H.R. 1526, and one motion to commit on S.J. Res. 18 and S.J. Res. 28.</text>
        <type>Floor</type>
        <actionCode>H12700</actionCode>
        <sourceSystem>
          <code>2</code>
          <name>House floor actions</name>
        </sourceSystem>
      </item>
      <item>
        <actionDate>2025-04-07</actionDate>
        <text>The House Committee on Rules reported an original measure, H. Rept. 119-50, by Ms. Foxx.</text>
        <type>Committee</type>
        <actionCode>H12100</actionCode>
        <sourceSystem>
          <code>2</code>
          <name>House floor actions</name>
        </sourceSystem>
        <committees>
          <item>
            <systemCode>hsru00</systemCode>
            <name>Rules Committee</name>
          </item>
        </committees>
      </item>
      <item>
        <actionDate>2025-04-07</actionDate>
        <text>The House Committee on Rules reported an original measure, H. Rept. 119-50, by Ms. Foxx.</text>
        <type>Committee</type>
        <actionCode>1010</actionCode>
        <sourceSystem>
          <code>9</code>
          <name>Library of Congress</name>
        </sourceSystem>
        <committees>
          <item>
            <systemCode>hsru00</systemCode>
            <name>Rules Committee</name>
          </item>
        </committees>
      </item>
    </actions>
    <sponsors>
      <item>
        <bioguideId>F000450</bioguideId>
        <fullName>Rep. Foxx, Virginia [R-NC-5]</fullName>
        <firstName>Virginia</firstName>
        <lastName>Foxx</lastName>
        <party>R</party>
        <state>NC</state>
        <district>5</district>
        <isByRequest>N</isByRequest>
      </item>
    </sponsors>
    <policyArea>
      <name>Congress</name>
    </policyArea>
    <subjects>
      <legislativeSubjects>
        <item>
          <name>House of Representatives</name>
          <updateDate>2025-04-09T13:21:59Z</updateDate>
        </item>
        <item>
          <name>Legislative rules and procedure</name>
          <updateDate>2025-04-09T13:22:05Z</updateDate>
        </item>
      </legislativeSubjects>
      <policyArea>
        <name>Congress</name>
        <updateDate>2025-04-08T16:40:52Z</updateDate>
      </policyArea>
    </subjects>
    <title>Providing for consideration of the joint resolution (S.J. Res. 18) disapproving the rule submitted by the Bureau of Consumer Financial Protection relating to "Overdraft Lending: Very Large Financial Institutions"; providing for consideration of the joint resolution (S.J. Res. 28) disapproving the rule submitted by the Bureau of Consumer Financial Protection relating to "Defining Larger Participants of a Market for General-Use Digital Consumer Payment Applications"; providing for consideration of the bill (H.R. 1526) to amend title 28, United States Code, to limit the authority of district courts to provide injunctive relief, and for other purposes; providing for consideration of the bill (H.R. 22) to amend the National Voter Registration Act of 1993 to require proof of United States citizenship to register an individual to vote in elections for Federal office, and for other purposes; and for other purposes.</title>
    <titles>
      <item>
        <titleType>Display Title</titleType>
        <titleTypeCode>45</titleTypeCode>
        <title>Providing for consideration of the joint resolution (S.J. Res. 18) disapproving the rule submitted by the Bureau of Consumer Financial Protection relating to "Overdraft Lending: Very Large Financial Institutions"; providing for consideration of the joint resolution (S.J. Res. 28) disapproving the rule submitted by the Bureau of Consumer Financial Protection relating to "Defining Larger Participants of a Market for General-Use Digital Consumer Payment Applications"; providing for consideration of the bill (H.R. 1526) to amend title 28, United States Code, to limit the authority of district courts to provide injunctive relief, and for other purposes; providing for consideration of the bill (H.R. 22) to amend the National Voter Registration Act of 1993 to require proof of United States citizenship to register an individual to vote in elections for Federal office, and for other purposes; and for other purposes.</title>
        <updateDate>2025-04-08T08:05:39Z</updateDate>
      </item>
      <item>
        <titleType>Official Title as Introduced</titleType>
        <titleTypeCode>6</titleTypeCode>
        <title>Providing for consideration of the joint resolution (S.J. Res. 18) disapproving the rule submitted by the Bureau of Consumer Financial Protection relating to "Overdraft Lending: Very Large Financial Institutions"; providing for consideration of the joint resolution (S.J. Res. 28) disapproving the rule submitted by the Bureau of Consumer Financial Protection relating to "Defining Larger Participants of a Market for General-Use Digital Consumer Payment Applications"; providing for consideration of the bill (H.R. 1526) to amend title 28, United States Code, to limit the authority of district courts to provide injunctive relief, and for other purposes; providing for consideration of the bill (H.R. 22) to amend the National Voter Registration Act of 1993 to require proof of United States citizenship to register an individual to vote in elections for Federal office, and for other purposes; and for other purposes.</title>
        <updateDate>2025-04-08T08:05:39Z</updateDate>
      </item>
    </titles>
    <textVersions>
      <item>
        <type>Engrossed in House</type>
        <date>2025-04-08T04:00:00Z</date>
        <formats>
          <item>
            <url>https://www.govinfo.gov/content/pkg/BILLS-119hres294eh/xml/BILLS-119hres294eh.xml</url>
          </item>
        </formats>
      </item>
      <item>
        <type>Reported in House</type>
        <date>2025-04-07T04:00:00Z</date>
        <formats>
          <item>
            <url>https://www.govinfo.gov/content/pkg/BILLS-119hres294rh/xml/BILLS-119hres294rh.xml</url>
          </item>
        </formats>
      </item>
    </textVersions>
    <latestAction>
      <actionDate>2025-04-08</actionDate>
      <text>Motion to reconsider laid on the table Agreed to without objection.</text>
      <actionTime>15:23:14</actionTime>
    </latestAction>
  </bill>
  <dublinCore xmlns:dc="http://purl.org/dc/elements/1.1/">
    <dc:format>text/xml</dc:format>
    <dc:language>EN</dc:language>
    <dc:rights>Pursuant to Title 17 Section 105 of the United States Code, this file is not subject to copyright protection and is in the public domain.</dc:rights>
    <dc:contributor>Congressional Research Service, Library of Congress</dc:contributor>
    <dc:description>This file contains bill summaries and statuses for federal legislation. A bill summary describes the most significant provisions of a piece of legislation and details the effects the legislative text may have on current law and federal programs. Bill summaries are authored by the Congressional Research Service (CRS) of the Library of Congress. As stated in Public Law 91-510 (2 USC 166 (d)(6)), one of the duties of CRS is "to prepare summaries and digests of bills and resolutions of a public general nature introduced in the Senate or House of Representatives". For more information, refer to the User Guide that accompanies this file.</dc:description>
  </dublinCore>
</billStatus>
